ZopeUndo/Prefix.py
ZopeUndo/__init__.py
ZopeUndo/tests/__init__.py
ZopeUndo/tests/test_prefix.py
ZopeUndo-6.0.dist-info/LICENSE.txt
ZopeUndo-6.0.dist-info/METADATA
ZopeUndo-6.0.dist-info/WHEEL
ZopeUndo-6.0.dist-info/top_level.txt
ZopeUndo-6.0.dist-info/RECORD
